[
  {
    "id": "center-001",
    "name": "Puri District Cyclone Shelter",
    "type": "Cyclone Shelter",
    "location": "Puri Town",
    "address": "Near Puri Railway Station, Grand Road",
    "coordinates": {"lat": 19.8135, "lon": 85.8312},
    "capacity": 5000,
    "current_occupancy": 3200,
    "facilities": ["Medical Unit", "Drinking Water", "Electricity", "Toilets", "Kitchen"],
    "contact": "+91-6752-223344",
    "status": "Active",
    "distance_from_coast": "2.5 km"
  },
  {
    "id": "center-002",
    "name": "Jagatsinghpur Multi-Purpose Cyclone Shelter",
    "type": "Cyclone Shelter",
    "location": "Jagatsinghpur",
    "address": "Jagatsinghpur College Campus",
    "coordinates": {"lat": 20.2542, "lon": 86.1711},
    "capacity": 3000,
    "current_occupancy": 1800,
    "facilities": ["Medical Unit", "Drinking Water", "Electricity", "Toilets", "Kitchen", "Generator"],
    "contact": "+91-6724-220055",
    "status": "Active",
    "distance_from_coast": "8 km"
  },
  {
    "id": "center-003",
    "name": "Kendrapara Flood Relief Center",
    "type": "Flood Shelter",
    "location": "Kendrapara Town",
    "address": "District Sports Complex",
    "coordinates": {"lat": 20.5020, "lon": 86.4220},
    "capacity": 2500,
    "current_occupancy": 950,
    "facilities": ["Medical Unit", "Drinking Water", "Toilets", "Kitchen"],
    "contact": "+91-6727-232323",
    "status": "Active",
    "distance_from_coast": "15 km"
  },
  {
    "id": "center-004",
    "name": "Bhadrak District Cyclone Shelter",
    "type": "Cyclone Shelter",
    "location": "Bhadrak Town",
    "address": "Government High School, Station Road",
    "coordinates": {"lat": 21.0542, "lon": 86.4936},
    "capacity": 4000,
    "current_occupancy": 2100,
    "facilities": ["Medical Unit", "Drinking Water", "Electricity", "Toilets", "Kitchen"],
    "contact": "+91-6784-251122",
    "status": "Active",
    "distance_from_coast": "20 km"
  },
  {
    "id": "center-005",
    "name": "Balasore Emergency Relief Center",
    "type": "Multi-Purpose Shelter",
    "location": "Balasore",
    "address": "Town Hall Complex",
    "coordinates": {"lat": 21.4934, "lon": 86.9336},
    "capacity": 3500,
    "current_occupancy": 0,
    "facilities": ["Medical Unit", "Drinking Water", "Electricity", "Toilets", "Kitchen", "Generator"],
    "contact": "+91-6782-262626",
    "status": "Standby",
    "distance_from_coast": "12 km"
  },
  {
    "id": "center-006",
    "name": "Cuttack Flood Relief Camp",
    "type": "Flood Shelter",
    "location": "Cuttack City",
    "address": "Barabati Stadium Complex",
    "coordinates": {"lat": 20.5124, "lon": 85.8828},
    "capacity": 6000,
    "current_occupancy": 450,
    "facilities": ["Medical Unit", "Drinking Water", "Electricity", "Toilets", "Kitchen"],
    "contact": "+91-671-2301234",
    "status": "Active",
    "distance_from_coast": "35 km"
  },
  {
    "id": "center-007",
    "name": "Khordha District Shelter",
    "type": "Multi-Purpose Shelter",
    "location": "Khordha Town",
    "address": "Community Hall, Jatni Road",
    "coordinates": {"lat": 20.1809, "lon": 85.6159},
    "capacity": 2000,
    "current_occupancy": 320,
    "facilities": ["Drinking Water", "Toilets", "Kitchen"],
    "contact": "+91-6755-220011",
    "status": "Active",
    "distance_from_coast": "30 km"
  },
  {
    "id": "center-008",
    "name": "Paradip Port Cyclone Shelter",
    "type": "Cyclone Shelter",
    "location": "Paradip",
    "address": "Near Paradip Port Authority",
    "coordinates": {"lat": 20.3150, "lon": 86.6094},
    "capacity": 3500,
    "current_occupancy": 2800,
    "facilities": ["Medical Unit", "Drinking Water", "Electricity", "Toilets", "Kitchen", "Generator"],
    "contact": "+91-6722-222555",
    "status": "Active",
    "distance_from_coast": "1 km"
  }
]